octreelib/__init__.py
octreelib/grid/__init__.py
octreelib/grid/grid.py
octreelib/grid/grid_base.py
octreelib/internal/__init__.py
octreelib/internal/interfaces.py
octreelib/internal/point.py
octreelib/internal/typing.py
octreelib/internal/voxel.py
octreelib/octree/__init__.py
octreelib/octree/octree.py
octreelib/octree/octree_base.py
octreelib/octree_manager/__init__.py
octreelib/octree_manager/octree_manager.py
octreelib/ransac/__init__.py
octreelib/ransac/cuda_ransac.py
octreelib/ransac/util.py
octreelib-0.0.9.dist-info/LICENSE
octreelib-0.0.9.dist-info/METADATA
octreelib-0.0.9.dist-info/WHEEL
octreelib-0.0.9.dist-info/RECORD
