Metadata-Version: 2.1
Name: octreelib
Version: 0.0.9
Summary: Library for representing point clouds as OcTrees in SLAM
Home-page: https://github.com/prime-slam/
License: APACHE
Author: Kiselyov Mikhail
Author-email: kiselev.0353@gmail.com
Requires-Python: >=3.9.0,<4.0.0
Classifier: Intended Audience :: Developers
Classifier: License :: OSI Approved :: Apache Software License
Classifier: License :: Other/Proprietary License
Classifier: Programming Language :: Python :: 3
Classifier: Programming Language :: Python :: 3.9
Classifier: Programming Language :: Python :: 3.10
Classifier: Programming Language :: Python :: 3.11
Classifier: Programming Language :: Python :: 3.12
Classifier: Topic :: Software Development :: Libraries :: Python Modules
Requires-Dist: k3d (>=2.16.0,<3.0.0)
Requires-Dist: numba (>=0.59.0,<0.60.0)
Requires-Dist: numpy (>=1.26.0,<2.0.0)
Project-URL: Repository, https://github.com/prime-slam/octreelib
